vkmusic
