Metadata-Version: 1.0
Name: VKMusic
Version: 0.1.3
Summary: Extremely small tool to export audios from vk.com
Home-page: http://korzhyk.github.com/VKMusic/
Author: Andrii Korzh
Author-email: Andrii.Korzh@gmail.com
License: BSD
Keywords: vk music
Platform: UNKNOWN
